aioevents/__init__.py
aioevents-0.2.dist-info/LICENSE
aioevents-0.2.dist-info/METADATA
aioevents-0.2.dist-info/WHEEL
aioevents-0.2.dist-info/RECORD
