Metadata-Version: 2.1
Name: aioevents
Version: 0.2
Summary: Events for asyncio
Home-page: https://github.com/AstraLuma/aioevents
License: MIT
Author: Jamie Bliss
Author-email: jamie@ivyleav.es
Requires-Python: >=3.11,<4.0
Classifier: License :: OSI Approved :: MIT License
Classifier: Programming Language :: Python :: 3
Classifier: Programming Language :: Python :: 3.11
Project-URL: Documentation, https://aioevents.readthedocs.io/
Project-URL: Repository, https://github.com/AstraLuma/aioevents
